MANIFEST.in
README.rst
requirements.txt
setup.py
desub/__init__.py
desub/desub.py
desub.egg-info/PKG-INFO
desub.egg-info/SOURCES.txt
desub.egg-info/dependency_links.txt
desub.egg-info/requires.txt
desub.egg-info/top_level.txt