Metadata-Version: 1.0
Name: desub
Version: 1.0.3
Summary: Work with a detached subprocess.
Home-page: https://github.com/kumar303/desub
Author: Kumar McMillan
Author-email: kumar.mcmillan@gmail.com
License: MIT
Platform: UNKNOWN
